{
  "type": "purrfect:handcrafting",
  "output": {
    "item": "purrfect:pride_flag",
    "count": 3
  },
  "ingredients": [
    {
      "ingredient": {
        "item": "purrfect:flagpole"
      },
      "count": 3
    },
    {
      "ingredient": {
        "item": "minecraft:purple_wool"
      },
      "count": 1
    },
    {
      "ingredient": {
        "item": "minecraft:blue_wool"
      },
      "count": 1
    },
    {
      "ingredient": {
        "item": "minecraft:green_wool"
      },
      "count": 1
    },
    {
      "ingredient": {
        "item": "minecraft:yellow_wool"
      },
      "count": 1
    },
    {
      "ingredient": {
        "item": "minecraft:orange_wool"
      },
      "count": 1
    },
    {
      "ingredient": {
        "item": "minecraft:red_wool"
      },
      "count": 1
    }
  ]
}