{
  "type": "purrfect:handcrafting",
  "output": {
    "item": "fluffy_fur:onjerlay_plush",
    "count": 1
  },
  "ingredients": [
    {
      "ingredient": {
        "tag": "forge:gems/diamond"
      },
      "count": 1
    },
    {
      "ingredient": {
        "item": "minecraft:note_block"
      },
      "count": 1
    },
    {
      "ingredient": {
        "item": "minecraft:yellow_wool"
      },
      "count": 6
    },
    {
      "ingredient": {
        "item": "minecraft:white_wool"
      },
      "count": 4
    }
  ]
}